vizier/__init__.py
vizier/__main__.py
vizier/mimir.py
vizier/wsgi.py
vizier/api/__init__.py
vizier/api/base.py
vizier/api/client/__init__.py
vizier/api/client/base.py
vizier/api/client/cli/__init__.py
vizier/api/client/cli/command.py
vizier/api/client/cli/interpreter.py
vizier/api/client/cli/notebook.py
vizier/api/client/cli/packages.py
vizier/api/client/cli/setting.py
vizier/api/client/cli/util.py
vizier/api/client/cli/viztrail.py
vizier/api/client/datastore/__init__.py
vizier/api/client/datastore/base.py
vizier/api/client/datastore/dataset.py
vizier/api/client/datastore/factory.py
vizier/api/client/resources/__init__.py
vizier/api/client/resources/branch.py
vizier/api/client/resources/chart.py
vizier/api/client/resources/dataset.py
vizier/api/client/resources/module.py
vizier/api/client/resources/notebook.py
vizier/api/client/resources/project.py
vizier/api/client/resources/view.py
vizier/api/client/resources/workflow.py
vizier/api/routes/__init__.py
vizier/api/routes/base.py
vizier/api/routes/container.py
vizier/api/routes/datastore.py
vizier/api/routes/task.py
vizier/api/serialize/__init__.py
vizier/api/serialize/base.py
vizier/api/serialize/branch.py
vizier/api/serialize/dataset.py
vizier/api/serialize/deserialize.py
vizier/api/serialize/dumper.py
vizier/api/serialize/files.py
vizier/api/serialize/hateoas.py
vizier/api/serialize/labels.py
vizier/api/serialize/module.py
vizier/api/serialize/project.py
vizier/api/serialize/view.py
vizier/api/serialize/workflow.py
vizier/api/webservice/__init__.py
vizier/api/webservice/base.py
vizier/api/webservice/branch.py
vizier/api/webservice/datastore.py
vizier/api/webservice/filestore.py
vizier/api/webservice/message.py
vizier/api/webservice/project.py
vizier/api/webservice/server.py
vizier/api/webservice/task.py
vizier/api/webservice/view.py
vizier/api/webservice/workflow.py
vizier/api/webservice/container/__init__.py
vizier/api/webservice/container/base.py
vizier/api/webservice/container/project.py
vizier_webapi-0.7.5.dist-info/LICENSE.txt
vizier_webapi-0.7.5.dist-info/METADATA
vizier_webapi-0.7.5.dist-info/WHEEL
vizier_webapi-0.7.5.dist-info/top_level.txt
vizier_webapi-0.7.5.dist-info/RECORD
